{
    "Determinants": [
        "each",
        "tiger",
        "some",
        "screw",
        "a few",
        "many",
        "cat",
        "pleasure",
        "my",
        "their",
        "frogs",
        "legs",
        "either",
        "strech",
        "wheels",
        "bear",
        "ten",
        "letetuces",
        "respect",
        "a",
        "back",
        "neighter",
        "word",
        "half",
        "your",
        "quite",
        "enough",
        "backs",
        "guns",
        "gun",
        "a lot of",
        "both",
        "tigers",
        "cats",
        "loaf",
        "throats",
        "much",
        "beers",
        "boot",
        "her",
        "a little",
        "an",
        "pens",
        "such",
        "one",
        "pen",
        "boots",
        "most",
        "wheel",
        "toy",
        "every",
        "apparatus",
        "his",
        "other",
        "its",
        "words",
        "thirty",
        "leg",
        "pleassures",
        "all",
        "these",
        "our",
        "loafs",
        "letetuce",
        "rather",
        "those",
        "swing",
        "what",
        "that",
        "throat",
        "frog",
        "another",
        "any",
        "streches",
        "the",
        "screws",
        "toys",
        "this",
        "swings"
    ],
    "Nouns": [
        "words",
        "leg",
        "loaf",
        "throats",
        "bear",
        "pleassures",
        "letetuces",
        "beers",
        "boot",
        "respect",
        "tiger",
        "screw",
        "loafs",
        "letetuce",
        "back",
        "pens",
        "swing",
        "pen",
        "cat",
        "boots",
        "pleasure",
        "word",
        "throat",
        "frog",
        "wheel",
        "toy",
        "frogs",
        "gun",
        "guns",
        "backs",
        "legs",
        "screws",
        "toys",
        "tigers",
        "apparatus",
        "cats",
        "swings",
        "wheels"
    ],
    "AuxiliaryVerb": [
        "ought",
        "need",
        "should",
        "must",
        "can",
        "shall",
        "have",
        "be",
        "would",
        "will",
        "do",
        "dare",
        "is",
        "might",
        "may",
        "could"
    ],
    "Verb": [
        "Coordinate",
        "Pass",
        "Chase",
        "Obtain",
        "Pull",
        "Quit",
        "Wish",
        "Identify",
        "Judge",
        "Go",
        "Budget",
        "balanced",
        "Volunteer",
        "Build",
        "Bring",
        "Renew",
        "Watch",
        "Tend",
        "Ride",
        "Achieve",
        "alliwing",
        "Want",
        "Fit",
        "administered",
        "accelerating",
        "Administer",
        "strech",
        "buying",
        "Continue",
        "Help",
        "Convince",
        "Illustrate",
        "Win",
        "Appear",
        "Knock",
        "applying",
        "bought",
        "Stop",
        "Teach",
        "Show",
        "Explain",
        "Happen",
        "Pay",
        "Make",
        "Appointing",
        "Fall",
        "Joke",
        "Follow",
        "Close",
        "Balance",
        "Assemble",
        "Generate",
        "administering",
        "Order",
        "Trap",
        "Compare",
        "Lie",
        "Revere",
        "Jump",
        "Introduce",
        "Shame",
        "Quack",
        "Yearn",
        "Measure",
        "Wave",
        "Inform",
        "Appoint",
        "Relate",
        "Choose",
        "Recommend",
        "Paint",
        "Wait",
        "Shower",
        "streched",
        "Write",
        "analyzed",
        "Howl",
        "Eat",
        "Talk",
        "Meet",
        "Sing",
        "Warm",
        "applied",
        "read",
        "Eating",
        "Accelerate",
        "Parse",
        "apply",
        "Observe",
        "assembling",
        "Communicate",
        "Open",
        "Allow",
        "achieved",
        "Suggest",
        "Keep",
        "Stick",
        "assembled",
        "Kill",
        "appearing",
        "streching",
        "Check",
        "Wear",
        "allowed",
        "accelerated",
        "Budgeted",
        "Fight",
        "Hurt",
        "Resist",
        "Submit",
        "Encourage",
        "Expect",
        "Shake",
        "Collect",
        "Ignore",
        "Imply",
        "Cut",
        "appointed",
        "Hide",
        "Performed",
        "Warn",
        "Value",
        "Reach",
        "Shock",
        "Swim",
        "Include",
        "Reset",
        "achieving",
        "Collaborate",
        "Pinch",
        "balancing",
        "Offer",
        "Listen",
        "Own",
        "appeared",
        "Speak",
        "Debate",
        "Decide",
        "Leave",
        "Eat\tEating",
        "budgeting",
        "Comment",
        "Retire",
        "Hate",
        "Learn",
        "Walk",
        "Specify",
        "Raise",
        "Analyze",
        "Melt",
        "Buy",
        "Like",
        "Earn"
    ],
    "Adjective": [
        "difficult",
        "fine",
        "cloudy",
        "friendly",
        "cruel",
        "blue-eyed",
        "jittery",
        "important",
        "angry",
        "funny",
        "better",
        "grieving",
        "courageous",
        "graceful",
        "famous",
        "defiant",
        "blue",
        "bad",
        "clear",
        "evil",
        "handsome",
        "vast",
        "enchanting",
        "determined",
        "tender",
        "awful",
        "grumpy",
        "uptight",
        "fancy",
        "drab",
        "filthy",
        "expensive",
        "clean",
        "annoying",
        "bored",
        "homely",
        "alive",
        "cheerful",
        "talented",
        "wandering",
        "upset",
        "attractive",
        "clever",
        "condemned",
        "homeless",
        "bright",
        "beautiful",
        "alert",
        "gleaming",
        "frantic",
        "tense",
        "colorful",
        "frail",
        "aggressive",
        "bloody",
        "energetic",
        "ugly",
        "curious",
        "annoyed",
        "inquisitive",
        "uninterested",
        "zealous",
        "adorable",
        "black",
        "itchy",
        "arrogant",
        "jealous",
        "good",
        "fragile",
        "unsightly",
        "ill",
        "horrible",
        "confused",
        "cooperative",
        "clumsy",
        "fantastic",
        "easy",
        "joyous",
        "glorious",
        "helpful",
        "cautious",
        "grotesque",
        "thoughtless",
        "defeated",
        "troubled",
        "gifted",
        "cute",
        "anxious",
        "blushing",
        "vivacious",
        "fierce",
        "amused",
        "impossible",
        "dangerous",
        "inexpensive",
        "brave",
        "elegant",
        "crowded",
        "terrible",
        "innocent",
        "tired",
        "fair",
        "tasty",
        "gorgeous",
        "victorious",
        "elated",
        "helpless",
        "dizzy",
        "bewildered",
        "hurt",
        "happy",
        "hungry",
        "delightful",
        "charming",
        "calm",
        "combative",
        "ugliest",
        "different",
        "envious",
        "disgusted",
        "dark",
        "eager",
        "excited",
        "busy",
        "adventurous",
        "dull",
        "embarrassed",
        "tough",
        "disturbed",
        "frightened",
        "worrisome",
        "kind",
        "crazy",
        "healthy",
        "exuberant",
        "thoughtful",
        "agreeable",
        "gentle",
        "concerned",
        "brainy",
        "foolish",
        "glamorous",
        "jolly",
        "breakable",
        "wicked",
        "zany",
        "faithful",
        "encouraging",
        "tame",
        "hilarious",
        "enthusiastic",
        "distinct",
        "careful",
        "depressed",
        "witty",
        "wrong",
        "weary",
        "creepy",
        "worried",
        "comfortable",
        "wide-eyed",
        "unusual",
        "wild",
        "dead",
        "doubtful",
        "thankful",
        "ashamed",
        "average"
    ],
    "Preposition": [
        "from",
        "at",
        "since",
        "by",
        "until",
        "in",
        "foe",
        "through",
        "between",
        "with",
        "about",
        "among",
        "towards",
        "of",
        "across",
        "on",
        "to"
    ],
    "ModifyingAdverb": [
        "so",
        "very",
        "really"
    ],
    "Adverb": [
        "sternly",
        "unexpectedly",
        "daily",
        "crazily",
        "deliberately",
        "vociferously",
        "boastfully",
        "weekly",
        "boldly",
        "badly",
        "occasionally",
        "often",
        "weakly",
        "noisily",
        "today",
        "awkwardly",
        "audibly",
        "dramatically",
        "lazily",
        "soundlessly",
        "blindly",
        "mortally",
        "deafeningly",
        "regularly",
        "sometimes",
        "speedily",
        "immediately",
        "shakily",
        "restlessly",
        "faintly",
        "accidentally",
        "swiftly",
        "brightly",
        "uproariously",
        "rapidly",
        "gradually",
        "dutifully",
        "promptly",
        "poorly",
        "tomorrow",
        "haltingly",
        "hourly",
        "cruelly",
        "normally",
        "still",
        "quickly",
        "loudly",
        "softly",
        "faithfully",
        "rarely",
        "wildly",
        "fortunately",
        "eventually",
        "doubtfully",
        "cheerfully",
        "instantly",
        "tediously",
        "hurriedly",
        "generally",
        "eagerly",
        "yearly",
        "noiselessly",
        "never",
        "leisurely",
        "soon",
        "wearily",
        "quietly",
        "frequently",
        "fleetingly",
        "coyly",
        "casually",
        "madly",
        "solemnly",
        "hastily",
        "nightly",
        "later",
        "seldom",
        "angrily",
        "expeditiously",
        "silently",
        "seriously",
        "emphatically",
        "mysteriously",
        "enormously",
        "inaudibly",
        "finally",
        "always",
        "resoundingly",
        "usually",
        "ear-splittingly",
        "defiantly",
        "hungrily",
        "languidly",
        "excitedly",
        "nervously",
        "yesterday",
        "shrilly",
        "gleefully",
        "slowly",
        "briskly",
        "resonantly",
        "thunderously"
    ]
}